pydataxm/__init__.py
pydataxm/pydatasimem.py
pydataxm/pydataxm.py
pydataxm-0.3.16.dist-info/LICENSE
pydataxm-0.3.16.dist-info/METADATA
pydataxm-0.3.16.dist-info/WHEEL
pydataxm-0.3.16.dist-info/top_level.txt
pydataxm-0.3.16.dist-info/RECORD
