Metadata-Version: 2.1
Name: pydataxm
Version: 0.3.16
Summary: Interface to interact with API XM and API SIMEM
Home-page: https://github.com/EquipoAnaliticaXM/API_XM
Download-URL: https://raw.githubusercontent.com/EquipoAnaliticaXM/API_XM/master/pydataxm/pydataxm.py
Author: Equipo Analitica XM
Author-email: analitica@xm.com.co
License: MIT
Classifier: Development Status :: 3 - Alpha
Classifier: Intended Audience :: Developers
Classifier: License :: OSI Approved :: MIT License
Classifier: Programming Language :: Python :: 3.10
Requires-Python: >=3.10
License-File: LICENSE
Requires-Dist: pandas >=2.2.3
Requires-Dist: numpy
Requires-Dist: requests
Requires-Dist: aiohttp
Requires-Dist: asyncio
Requires-Dist: nest-asyncio
